BenFangfaXueRuby/README.md
BenFangfaXueRuby/__init__.py
BenFangfaXueRuby/__main__.py
BenFangfaXueRuby/file.epub
BenFangfaXueRuby/index.html
BenFangfaXueRuby/css/__init__.py
BenFangfaXueRuby/css/annotations.css
BenFangfaXueRuby/css/main.css
BenFangfaXueRuby/css/normalize.css
BenFangfaXueRuby/css/popup.css
BenFangfaXueRuby/font/__init__.py
BenFangfaXueRuby/font/fontello.eot
BenFangfaXueRuby/font/fontello.svg
BenFangfaXueRuby/font/fontello.ttf
BenFangfaXueRuby/font/fontello.woff
BenFangfaXueRuby/img/__init__.py
BenFangfaXueRuby/img/annotator-glyph-sprite.png
BenFangfaXueRuby/img/annotator-icon-sprite.png
BenFangfaXueRuby/img/apple-touch-icon.png
BenFangfaXueRuby/img/cancelfullscreen.png
BenFangfaXueRuby/img/close.png
BenFangfaXueRuby/img/fullscreen.png
BenFangfaXueRuby/img/loader.gif
BenFangfaXueRuby/img/menu-icon.png
BenFangfaXueRuby/img/save.png
BenFangfaXueRuby/img/saved.png
BenFangfaXueRuby/img/settings-s.png
BenFangfaXueRuby/img/settings.png
BenFangfaXueRuby/img/star.png
BenFangfaXueRuby/js/__init__.py
BenFangfaXueRuby/js/epub.js
BenFangfaXueRuby/js/epub.min.js
BenFangfaXueRuby/js/epub.min.map
BenFangfaXueRuby/js/hooks.min.js
BenFangfaXueRuby/js/hooks.min.map
BenFangfaXueRuby/js/reader.js
BenFangfaXueRuby/js/reader.js.map
BenFangfaXueRuby/js/reader.min.js
BenFangfaXueRuby/js/reader.min.map
BenFangfaXueRuby/js/hooks/__init__.py
BenFangfaXueRuby/js/hooks/extensions/__init__.py
BenFangfaXueRuby/js/hooks/extensions/highlight.js
BenFangfaXueRuby/js/libs/__init__.py
BenFangfaXueRuby/js/libs/jquery.min.js
BenFangfaXueRuby/js/libs/localforage.min.js
BenFangfaXueRuby/js/libs/screenfull.js
BenFangfaXueRuby/js/libs/screenfull.min.js
BenFangfaXueRuby/js/libs/zip.min.js
BenFangfaXueRuby/js/plugins/__init__.py
BenFangfaXueRuby/js/plugins/hypothesis.js
BenFangfaXueRuby/js/plugins/search.js
ben_fangfa_xue_ruby-2024.3.1.0.dist-info/METADATA
ben_fangfa_xue_ruby-2024.3.1.0.dist-info/WHEEL
ben_fangfa_xue_ruby-2024.3.1.0.dist-info/entry_points.txt
ben_fangfa_xue_ruby-2024.3.1.0.dist-info/top_level.txt
ben_fangfa_xue_ruby-2024.3.1.0.dist-info/RECORD
